business_rules2/__init__.py
business_rules2/actions.py
business_rules2/engine.py
business_rules2/fields.py
business_rules2/operators.py
business_rules2/parser.py
business_rules2/syntaxcheck.py
business_rules2/test_parse.py
business_rules2/utils.py
business_rules2/variables.py
business_rules2-1.1.5.dist-info/LICENSE
business_rules2-1.1.5.dist-info/METADATA
business_rules2-1.1.5.dist-info/WHEEL
business_rules2-1.1.5.dist-info/top_level.txt
business_rules2-1.1.5.dist-info/RECORD
